vitenv/__init__.py
vitenv/envconfig_firemen.py
vitenv/envconfig_navigation.py
vitenv/environment.py
vitenv/firemen.py
vitenv/minimap_v1.py
vitenv/minimap_v2.py
vitenv/minimap_v3.py
vitenv/minimapworld.py
vitenv/navigation.py
vitenv-0.0.4.dist-info/METADATA
vitenv-0.0.4.dist-info/WHEEL
vitenv-0.0.4.dist-info/top_level.txt
vitenv-0.0.4.dist-info/RECORD
